needls/__init__.py
needls/__main__.py
needls/exceptions.py
needls/needs_store.py
needls/server.py
needls/version.py
open_needs_ls-0.0.18.dist-info/AUTHORS
open_needs_ls-0.0.18.dist-info/LICENSE
open_needs_ls-0.0.18.dist-info/METADATA
open_needs_ls-0.0.18.dist-info/WHEEL
open_needs_ls-0.0.18.dist-info/top_level.txt
open_needs_ls-0.0.18.dist-info/RECORD
