Metadata-Version: 2.1
Name: open-needs-ls
Version: 0.0.18
Summary: Open-Neeeds JSON RPC server implementing Microsoft Language Server Protocol
Home-page: https://open-needs.org
Author: Daniel Woste
Author-email: daniel.woste@useblocks.com
License: UNKNOWN
Platform: UNKNOWN
License-File: LICENSE
License-File: AUTHORS
Requires-Dist: pygls (>=0.11.0)
